dextop.cpython-313-aarch64-linux-gnu.so
dextop/proto/dexcontrol_query_pb2.pyi
dextop/proto/soc_internal_pb2.pyi
dextop.build/.gitignore
dextop-0.3.5.dist-info/METADATA
dextop-0.3.5.dist-info/WHEEL
dextop-0.3.5.dist-info/entry_points.txt
dextop-0.3.5.dist-info/top_level.txt
dextop-0.3.5.dist-info/RECORD
dextop-0.3.5.dist-info/licenses/LICENSE
