Metadata-Version: 2.4
Name: dextop
Version: 0.3.5
Summary: A command line tool for managing and configuring Dexmate robot interfaces. Provides utilities for robot management, connection discovery, and interface configuration.
Author-email: Dexmate <contact@dexmate.com>
Maintainer-email: Dexmate <contact@dexmate.com>
License-Expression: AGPL-3.0
Keywords: cli,management,interface,dexmate
Classifier: Programming Language :: Python :: 3.10
Classifier: Programming Language :: Python :: 3.11
Classifier: Programming Language :: Python :: 3.12
Classifier: Programming Language :: Python :: 3.13
Classifier: Operating System :: POSIX :: Linux
Classifier: Development Status :: 4 - Beta
Classifier: Intended Audience :: Developers
Classifier: Topic :: Software Development :: Libraries :: Python Modules
Requires-Python: >=3.10
License-File: LICENSE
Requires-Dist: cryptography>=3.4.7
Requires-Dist: typer>=0.15.0
Requires-Dist: eclipse-zenoh>=1.2.0
Requires-Dist: paramiko>=3.5.1
Requires-Dist: loguru>=0.7.3
Requires-Dist: protobuf>=6.31.0
Requires-Dist: rich>=14.0.0
Requires-Dist: wonderwords>=2.2.0
Requires-Dist: zstandard>=0.23.0
Requires-Dist: httpx>=0.27.0
Dynamic: license-file
